README.txt
setup.cfg
setup.py
docs/HISTORY.txt
haufe/__init__.py
haufe.sortabletable.egg-info/PKG-INFO
haufe.sortabletable.egg-info/SOURCES.txt
haufe.sortabletable.egg-info/dependency_links.txt
haufe.sortabletable.egg-info/entry_points.txt
haufe.sortabletable.egg-info/namespace_packages.txt
haufe.sortabletable.egg-info/not-zip-safe
haufe.sortabletable.egg-info/requires.txt
haufe.sortabletable.egg-info/top_level.txt
haufe/sortabletable/__init__.py
haufe/sortabletable/configure.zcml
haufe/sortabletable/profiles.zcml
haufe/sortabletable/profiles/default/skins.xml
haufe/sortabletable/skins/sortabletable/datesorttype.js
haufe/sortabletable/skins/sortabletable/datesorttype.js.metadata
haufe/sortabletable/skins/sortabletable/germandatesorttype.js
haufe/sortabletable/skins/sortabletable/germandatesorttype.js.metadata
haufe/sortabletable/skins/sortabletable/hidxsorttype.js
haufe/sortabletable/skins/sortabletable/hidxsorttype.js.metadata
haufe/sortabletable/skins/sortabletable/numberksorttype.js
haufe/sortabletable/skins/sortabletable/numberksorttype.js.metadata
haufe/sortabletable/skins/sortabletable/sortabletable.css
haufe/sortabletable/skins/sortabletable/sortabletable.js
haufe/sortabletable/skins/sortabletable/sortabletable.js.metadata
haufe/sortabletable/skins/sortabletable/sortabletable_blank.png
haufe/sortabletable/skins/sortabletable/sortabletable_downsimple.png
haufe/sortabletable/skins/sortabletable/sortabletable_upsimple.png
haufe/sortabletable/skins/sortabletable/stringbuilder.js
haufe/sortabletable/skins/sortabletable/stringbuilder.js.metadata
haufe/sortabletable/skins/sortabletable/uscurrencysorttype.js
haufe/sortabletable/skins/sortabletable/uscurrencysorttype.js.metadata