Metadata-Version: 1.1
Name: haufe.sortabletable
Version: 0.2
Summary: Sortabletable implementation as used in HRS2
Home-page: UNKNOWN
Author: Andreas Jung
Author-email: info@zopyx.com
License: GPL
Platform: UNKNOWN
Classifier: Programming Language :: Python
Classifier: Topic :: Software Development :: Libraries :: Python Modules
